jumpy/__init__.py
jumpy/java_classes.py
jumpy/matlib.py
jumpy/memory_manager.py
jumpy/ndarray.py
jumpy/tf_model.py
jumpy/ops/__init__.py
jumpy/ops/array_manip.py
jumpy/ops/linalg.py
jumpy/ops/op.py
jumpy/ops/reduction.py
jumpy-0.2.4.dist-info/METADATA
jumpy-0.2.4.dist-info/RECORD
jumpy-0.2.4.dist-info/WHEEL
jumpy-0.2.4.dist-info/top_level.txt
tests/__init__.py
tests/jumpy/__init__.py
tests/jumpy/test_array_creation.py
